llama2_wrapper/__init__.py
llama2_wrapper/download/__init__.py
llama2_wrapper/download/__main__.py
llama2_wrapper/model.py
llama2_wrapper/server/__init__.py
llama2_wrapper/server/__main__.py
llama2_wrapper/server/app.py
llama2_wrapper/types.py
llama2_wrapper-0.1.14.dist-info/LICENSE
llama2_wrapper-0.1.14.dist-info/METADATA
llama2_wrapper-0.1.14.dist-info/WHEEL
llama2_wrapper-0.1.14.dist-info/RECORD
