Metadata-Version: 2.1
Name: llama2-wrapper
Version: 0.1.14
Summary: Use llama2-wrapper as your local llama2 backend for Generative Agents / Apps
Home-page: https://github.com/liltom-eth/llama2-webui
License: MIT
Author: liltom-eth
Author-email: liltom.eth@gmail.com
Requires-Python: >=3.10,<3.13
Classifier: License :: OSI Approved :: MIT License
Classifier: Programming Language :: Python :: 3
Classifier: Programming Language :: Python :: 3.10
Classifier: Programming Language :: Python :: 3.11
Requires-Dist: accelerate (>=0.21.0,<0.22.0)
Requires-Dist: auto-gptq (==0.3.0)
Requires-Dist: bitsandbytes (==0.40.2) ; sys_platform == "darwin"
Requires-Dist: bitsandbytes (==0.40.2) ; sys_platform == "linux"
Requires-Dist: black (==23.7.0)
Requires-Dist: fastapi (==0.100.0)
Requires-Dist: gradio (==3.37.0)
Requires-Dist: huggingface-hub (==0.16.4)
Requires-Dist: llama-cpp-python (>=0.2.11,<0.3.0)
Requires-Dist: memory-profiler (==0.61.0)
Requires-Dist: protobuf (==3.20.3)
Requires-Dist: pydantic (==2.2.1)
Requires-Dist: pydantic-settings (==2.0.3)
Requires-Dist: pytest (==7.4.0)
Requires-Dist: python-dotenv (==1.0.0)
Requires-Dist: scipy (==1.11.1)
Requires-Dist: sentencepiece (==0.1.99)
Requires-Dist: sse-starlette (==1.6.5)
Requires-Dist: torch (==2.0.1)
Requires-Dist: tqdm (==4.65.0)
Requires-Dist: transformers (==4.31.0)
Requires-Dist: uvicorn (==0.23.1)
Project-URL: Repository, https://github.com/liltom-eth/llama2-webui
